quantjourney_bidask/__init__.py
quantjourney_bidask/_compare_edge.py
quantjourney_bidask/edge.py
quantjourney_bidask/edge_expanding.py
quantjourney_bidask/edge_hft.py
quantjourney_bidask/edge_rolling.py
quantjourney_bidask-1.0.2.dist-info/licenses/LICENSE
quantjourney_bidask-1.0.2.dist-info/METADATA
quantjourney_bidask-1.0.2.dist-info/WHEEL
quantjourney_bidask-1.0.2.dist-info/top_level.txt
quantjourney_bidask-1.0.2.dist-info/RECORD
