Metadata-Version: 2.4
Name: quantjourney-bidask
Version: 1.0.2
Summary: Efficient bid-ask spread estimator from OHLC prices
Author-email: Jakub Polec <jakub@quantjourney.pro>
License: MIT
Project-URL: Homepage, https://github.com/QuantJourneyOrg/quantjourney-bidask
Project-URL: Repository, https://github.com/QuantJourneyOrg/quantjourney-bidask
Project-URL: Bug Tracker, https://github.com/QuantJourneyOrg/quantjourney-bidask/issues
Keywords: finance,bid-ask,spread,trading,quantitative,OHLC
Classifier: Development Status :: 4 - Beta
Classifier: Intended Audience :: Financial and Insurance Industry
Classifier: Operating System :: OS Independent
Classifier: Programming Language :: Python :: 3
Classifier: Programming Language :: Python :: 3.11
Classifier: Programming Language :: Python :: 3.12
Classifier: Topic :: Office/Business :: Financial :: Investment
Classifier: Topic :: Software Development :: Libraries :: Python Modules
Requires-Python: <3.15,>=3.11
License-File: LICENSE
Requires-Dist: numpy>=1.20
Requires-Dist: pandas>=1.5
Requires-Dist: requests>=2.28
Requires-Dist: yfinance>=0.2
Requires-Dist: matplotlib>=3.5
Requires-Dist: plotly>=5.0
Requires-Dist: websocket-client>=1.0
Requires-Dist: numba
Provides-Extra: dev
Requires-Dist: pytest>=7.0; extra == "dev"
Requires-Dist: pytest-mock>=3.10; extra == "dev"
Requires-Dist: pytest-cov>=4.0; extra == "dev"
Requires-Dist: ruff>=0.1; extra == "dev"
Requires-Dist: mypy>=1.0; extra == "dev"
Requires-Dist: black>=22.0; extra == "dev"
Requires-Dist: isort>=5.0; extra == "dev"
Requires-Dist: numba; extra == "dev"
Provides-Extra: examples
Requires-Dist: jupyter>=1.0; extra == "examples"
Requires-Dist: ipywidgets>=7.0; extra == "examples"
Dynamic: license-file
